{"arrDungeons":[{"Name":"Sastasha","Category":"arrDungeons","MaxID":"783","MaxAltID":"663","Bold":true,"Spoilers":true},{"Name":"The Tam-Tara Deepcroft","Category":"arrDungeons","ID":"669","Bold":true,"Spoilers":true},{"Name":"Copperbell Mines","Category":"arrDungeons","MaxID":"783","MaxAltID":"666","Bold":true,"Spoilers":true},{"Name":"Halatali","Category":"arrDungeons","ID":"667"},{"Name":"The Thousand Maws of Toto-Rak","Category":"arrDungeons","MaxID":"783","MaxAltID":"673","Bold":true,"Spoilers":true},{"Name":"Haukke Manor","Category":"arrDungeons","MinID":"783","MaxID":"784","MaxAltID":"670","Bold":true,"Spoilers":true},{"Name":"Brayflox's Longstop","Category":"arrDungeons","MinID":"784","MaxID":"785","MaxAltID":"674","Bold":true,"Spoilers":true},{"Name":"The Sunken Temple of Qarn","Category":"arrDungeons","MaxAltID":"668"},{"Name":"Cutter's Cry","Category":"arrDungeons","ID":"674"},{"Name":"The Stone Vigil","Category":"arrDungeons","ID":"672","Bold":true,"Spoilers":true},{"Name":"Dzemael Darkhold","Category":"arrDungeons","MaxAltID":"675"},{"Name":"The Aurum Vale","Category":"arrDungeons","ID":"676"},{"Name":"The Wanderer's Palace","Category":"arrDungeons","ID":"665"},{"Name":"Castrum Meridianum","Category":"arrDungeons","MinID":"787","MaxID":"788","MaxAltID":"678","Bold":true,"Spoilers":true},{"Name":"The Praetorium","Category":"arrDungeons","MinID":"787","MaxID":"788","MaxAltID":"679","Bold":true,"Spoilers":true},{"Name":"Amdapor Keep","Category":"arrDungeons","ID":"671"},{"Name":"Pharos Sirius","Category":"arrDungeons","ID":"873"},{"Name":"Copperbell Mines (Hard)","Category":"arrDungeons","ID":"871","Spoilers":true,"SpoilersUntil":"783"},{"Name":"Haukke Manor (Hard)","Category":"arrDungeons","ID":"872","Spoilers":true,"SpoilersUntil":"784"},{"Name":"The Lost City of Amdapor","Category":"arrDungeons","ID":"897"},{"Name":"Halatali (Hard)","Category":"arrDungeons","ID":"895"},{"Name":"Brayflox's Longstop (Hard)","Category":"arrDungeons","ID":"896","Spoilers":true,"SpoilersUntil":"785"},{"Name":"Hullbreaker Isle","Category":"arrDungeons","ID":"993"},{"Name":"The Stone Vigil (Hard)","Category":"arrDungeons","ID":"992","Spoilers":true,"SpoilersUntil":"786"},{"Name":"The Tam-Tara Deepcroft (Hard)","Category":"arrDungeons","ID":"991","Spoilers":true,"SpoilersUntil":"783"},{"Name":"Snowcloak","Category":"arrDungeons","ID":"1039","Bold":true,"Spoilers":true},{"Name":"Sastasha (Hard)","Category":"arrDungeons","ID":"1038","Spoilers":true,"SpoilersUntil":"783"},{"Name":"The Sunken Temple of Qarn (Hard)","Category":"arrDungeons","ID":"1037"},{"Name":"The Keeper of the Lake","Category":"arrDungeons","ID":"1072","Bold":true,"Spoilers":true},{"Name":"The Wanderer's Palace (Hard)","Category":"arrDungeons","ID":"1071"},{"Name":"Amdapor Keep (Hard)","Category":"arrDungeons","ID":"1070"}],"hwDungeons":[{"Name":"The Dusk Vigil","Category":"hwDungeons","ID":"1208","Bold":true,"Spoilers":true},{"Name":"Sohm Al","Category":"hwDungeons","ID":"1209","Bold":true,"Spoilers":true},{"Name":"The Aery","Category":"hwDungeons","ID":"1210","Bold":true,"Spoilers":true},{"Name":"The Vault","Category":"hwDungeons","ID":"1211","Bold":true,"Spoilers":true},{"Name":"The Great Gubal Library","Category":"hwDungeons","ID":"1212","Bold":true,"Spoilers":true},{"Name":"The Aetherochemical Research Facility","Category":"hwDungeons","ID":"1213","Bold":true,"Spoilers":true},{"Name":"Neverreap","Category":"hwDungeons","ID":"1214"},{"Name":"The Fractal Continuum","Category":"hwDungeons","ID":"1215"},{"Name":"Saint Mocianne's Arboretum","Category":"hwDungeons","ID":"1402"},{"Name":"Pharos Sirius (Hard)","Category":"hwDungeons","ID":"1403"},{"Name":"The Antitower","Category":"hwDungeons","ID":"1486","Bold":true,"Spoilers":true},{"Name":"The Lost City of Amdapor (Hard)","Category":"hwDungeons","ID":"1487"},{"Name":"Sohr Khai","Category":"hwDungeons","ID":"1599","Bold":true,"Spoilers":true},{"Name":"Hullbreaker Isle (Hard)","Category":"hwDungeons","ID":"1600"},{"Name":"Xelphatol","Category":"hwDungeons","ID":"1637","Bold":true,"Spoilers":true},{"Name":"The Great Gubal Library (Hard)","Category":"hwDungeons","ID":"1638","Spoilers":true,"SpoilersUntil":"1212"},{"Name":"Baelsar's Wall","Category":"hwDungeons","ID":"1686","Bold":true,"Spoilers":true},{"Name":"Sohm Al (Hard)","Category":"hwDungeons","ID":"1687","Spoilers":true,"SpoilersUntil":"1209"}],"sbDungeons":[{"Name":"The Sirensong Sea","Category":"sbDungeons","ID":"1883","Bold":true,"Spoilers":true},{"Name":"Shisui of the Violet Tides","Category":"sbDungeons","ID":"1884","Bold":true,"Spoilers":true},{"Name":"Bardam's Mettle","Category":"sbDungeons","ID":"1885","Bold":true,"Spoilers":true},{"Name":"Doma Castle","Category":"sbDungeons","ID":"1886","Bold":true,"Spoilers":true},{"Name":"Castrum Abania","Category":"sbDungeons","ID":"1887","Bold":true,"Spoilers":true},{"Name":"Ala Mhigo","Category":"sbDungeons","ID":"1888","Bold":true,"Spoilers":true},{"Name":"Kugane Castle","Category":"sbDungeons","ID":"1889"},{"Name":"The Temple of the Fist","Category":"sbDungeons","ID":"1890"},{"Name":"The Drowned City of Skalla","Category":"sbDungeons","ID":"1988","Bold":true,"Spoilers":true},{"Name":"Hells' Lid","Category":"sbDungeons","ID":"2021"},{"Name":"The Fractal Continuum (Hard)","Category":"sbDungeons","ID":"2022"},{"Name":"The Swallow's Compass","Category":"sbDungeons","ID":"2057"},{"Name":"The Burn","Category":"sbDungeons","ID":"2115","Bold":true,"Spoilers":true},{"Name":"Saint Mocianne's Arboretum (Hard)","Category":"sbDungeons","ID":"2116"},{"Name":"The Ghimlyt Dark","Category":"sbDungeons","ID":"2162","Bold":true,"Spoilers":true}],"shbDungeons":[{"Name":"Holminster Switch","Category":"shbDungeons","ID":"2377","Bold":true,"Spoilers":true},{"Name":"Dohn Mheg","Category":"shbDungeons","ID":"2378","Bold":true,"Spoilers":true},{"Name":"The Qitana Ravel","Category":"shbDungeons","ID":"2379","Bold":true,"Spoilers":true},{"Name":"Malikah's Well","Category":"shbDungeons","ID":"2380","Bold":true,"Spoilers":true},{"Name":"Mt. Gulg","Category":"shbDungeons","ID":"2381","Bold":true,"Spoilers":true},{"Name":"Amaurot","Category":"shbDungeons","ID":"2382","Bold":true,"Spoilers":true},{"Name":"The Twinning","Category":"shbDungeons","ID":"2383"},{"Name":"Akadaemia Anyder","Category":"shbDungeons","ID":"2384"},{"Name":"The Grand Cosmos","Category":"shbDungeons","ID":"2440","Bold":true,"Spoilers":true},{"Name":"Anamnesis Anyder","Category":"shbDungeons","ID":"2589","Bold":true,"Spoilers":true},{"Name":"The Heroes' Gauntlet","Category":"shbDungeons","ID":"2618","Bold":true,"Spoilers":true},{"Name":"Matoya's Relict","Category":"shbDungeons","ID":"2717","Bold":true,"Spoilers":true},{"Name":"Paglth'an","Category":"shbDungeons","ID":"2849","Bold":true,"Spoilers":true}],"arrTrials":[{"Name":"The Bowl of Embers","Category":"arrTrials","MaxID":"783","Bold":true,"Spoilers":true},{"Name":"The Navel","Category":"arrTrials","MinID":"784","MaxID":"785","Bold":true,"Spoilers":true},{"Name":"The Howling Eye","Category":"arrTrials","MinID":"786","MaxID":"787","Bold":true,"Spoilers":true},{"Name":"Cape Westwind","Category":"arrTrials","MinID":"787","MaxID":"788","Bold":true,"Spoilers":true},{"Name":"The Chrysalis","Category":"arrTrials","ID":"1067","MinID":"1029","MaxID":"1129","Bold":true,"Spoilers":true},{"Name":"The Steps of Faith","Category":"arrTrials","ID":"1065","MinID":"1029","MaxID":"1129","Bold":true,"Spoilers":true},{"Name":"A Relic Reborn: The Chimera","Category":"arrTrials","MinID":"788","MaxID":"925"},{"Name":"A Relic Reborn: The Hydra","Category":"arrTrials","MinID":"788","MaxID":"925"},{"Name":"Battle on the Big Bridge","Category":"arrTrials","MinID":"788","MaxID":"1061"},{"Name":"The Dragon's Neck","Category":"arrTrials","MinID":"788","MaxID":"1061"},{"Name":"Battle in the Big Keep","Category":"arrTrials","ID":"1066"},{"Name":"The Bowl of Embers (Hard)","Category":"arrTrials","MinID":"788","MaxID":"747","MaxAltID":"855","Spoilers":true,"SpoilersUntil":"783"},{"Name":"The Howling Eye (Hard)","Category":"arrTrials","MinID":"788","MaxID":"747","MaxAltID":"856","Spoilers":true,"SpoilersUntil":"787"},{"Name":"The Navel (Hard)","Category":"arrTrials","MinID":"788","MaxID":"747","MaxAltID":"857","Spoilers":true,"SpoilersUntil":"785"},{"Name":"Thornmarch (Hard)","Category":"arrTrials","MinID":"788","MaxID":"898","Bold":true,"Spoilers":true},{"Name":"The Whorleater (Hard)","Category":"arrTrials","MinID":"898","MaxID":"899","Bold":true,"Spoilers":true},{"Name":"The Striking Tree (Hard)","Category":"arrTrials","MinID":"899","MaxID":"1001","Bold":true,"Spoilers":true},{"Name":"Akh Afah Amphitheatre (Hard)","Category":"arrTrials","MinID":"1001","MaxID":"1029","Bold":true,"Spoilers":true},{"Name":"Urth's Fount","Category":"arrTrials","ID":"1064","MinID":"788"}],"hwTrials":[{"Name":"Thok ast Thok (Hard)","Category":"hwTrials","MinID":"1134","MaxID":"1135","Bold":true,"Spoilers":true},{"Name":"The Limitless Blue (Hard)","Category":"hwTrials","MinID":"1136","MaxID":"1137","Bold":true,"Spoilers":true},{"Name":"The Singularity Reactor","Category":"hwTrials","MinID":"1138","MaxID":"1139","Bold":true,"Spoilers":true},{"Name":"The Final Steps of Faith","Category":"hwTrials","MinID":"1493","MaxID":"1594","Bold":true,"Spoilers":true},{"Name":"Containment Bay S1T7","Category":"hwTrials","MinID":"1139","MaxAltID":"1485"},{"Name":"Containment Bay P1T6","Category":"hwTrials","MinID":"1139","MaxAltID":"1636"},{"Name":"Containment Bay Z1T9","Category":"hwTrials","MinID":"1139","MaxAltID":"1685"}],"sbTrials":[{"Name":"The Pool of Tribute","Category":"sbTrials","MinID":"1788","MaxID":"1789","Bold":true,"Spoilers":true},{"Name":"Emanation","Category":"sbTrials","MinID":"1792","MaxID":"1793","Bold":true,"Spoilers":true},{"Name":"The Royal Menagerie","Category":"sbTrials","MinID":"1793","MaxID":"1794","Bold":true,"Spoilers":true},{"Name":"Castrum Fluminis","Category":"sbTrials","MinID":"2013","MaxID":"2098","Bold":true,"Spoilers":true},{"Name":"Kugane Ohashi","Category":"sbTrials","ID":"2236"},{"Name":"The Great Hunt","Category":"sbTrials","ID":"2108"},{"Name":"The Jade Stoa","Category":"sbTrials","MinID":"2057","MaxAltID":"2023"},{"Name":"Hells' Kier","Category":"sbTrials","MinID":"2057","MaxAltID":"2117"},{"Name":"The Wreath of Snakes","Category":"sbTrials","MinID":"2057","MaxAltID":"2165"}],"shbTrials":[{"Name":"The Dancing Plague","Category":"shbTrials","MinID":"2293","MaxID":"2294","Bold":true,"Spoilers":true},{"Name":"The Crown of the Immaculate","Category":"shbTrials","MinID":"2296","MaxID":"2297","Bold":true,"Spoilers":true},{"Name":"The Dying Gasp","Category":"shbTrials","MinID":"2297","MaxID":"2298","Bold":true,"Spoilers":true},{"Name":"Cinder Drift","Category":"shbTrials","MinID":"2424","MaxID":"2887","MaxAltID":"2590"},{"Name":"The Seat of Sacrifice","Category":"shbTrials","MinID":"2587","MaxID":"2642","Bold":true,"Spoilers":true},{"Name":"Castrum Marinum","Category":"shbTrials","MinID":"2424","MaxID":"2887","MaxAltID":"2718"},{"Name":"The Cloud Deck","Category":"shbTrials","MinID":"2424","MaxID":"2887","MaxAltID":"2846"}],"arrTrialsEx":[{"Name":"The Minstrel's Ballad: Ultima's Bane","Category":"arrTrialsEx","MaxID":"1000","Spoilers":true,"SpoilersUntil":"788"},{"Name":"The Howling Eye (Extreme)","Category":"arrTrialsEx","ID":"856","Spoilers":true,"SpoilersUntil":"787"},{"Name":"The Navel (Extreme)","Category":"arrTrialsEx","ID":"857","Spoilers":true,"SpoilersUntil":"785"},{"Name":"The Bowl of Embers (Extreme)","Category":"arrTrialsEx","ID":"855","Spoilers":true,"SpoilersUntil":"783"},{"Name":"Thornmarch (Extreme)","Category":"arrTrialsEx","ID":"894","Spoilers":true,"SpoilersUntil":"898"},{"Name":"The Whorleater (Extreme)","Category":"arrTrialsEx","ID":"893","Spoilers":true,"SpoilersUntil":"899"},{"Name":"The Striking Tree (Extreme)","Category":"arrTrialsEx","ID":"994","Spoilers":true,"SpoilersUntil":"1001"},{"Name":"Akh Afah Amphitheatre (Extreme)","Category":"arrTrialsEx","ID":"1045","Spoilers":true,"SpoilersUntil":"1029"}],"hwTrialsEx":[{"Name":"The Limitless Blue (Extreme)","Category":"hwTrialsEx","ID":"1220","Spoilers":true,"SpoilersUntil":"1137"},{"Name":"Thok ast Thok (Extreme)","Category":"hwTrialsEx","ID":"1221","Spoilers":true,"SpoilersUntil":"1135"},{"Name":"The Minstrel's Ballad: Thordan's Reign","Category":"hwTrialsEx","ID":"1400","Spoilers":true,"SpoilersUntil":"1139"},{"Name":"The Minstrel's Ballad: Nidhogg's Rage","Category":"hwTrialsEx","ID":"1601","Spoilers":true,"SpoilersUntil":"1594"},{"Name":"Containment Bay S1T7 (Extreme)","Category":"hwTrialsEx","ID":"1485"},{"Name":"Containment Bay P1T6 (Extreme)","Category":"hwTrialsEx","ID":"1636"},{"Name":"Containment Bay Z1T9 (Extreme)","Category":"hwTrialsEx","ID":"1685"}],"sbTrialsEx":[{"Name":"The Pool of Tribute (Extreme)","Category":"sbTrialsEx","ID":"1902","Spoilers":true,"SpoilersUntil":"1789"},{"Name":"Emanation (Extreme)","Category":"sbTrialsEx","ID":"1901","Spoilers":true,"SpoilersUntil":"1793"},{"Name":"The Minstrel's Ballad: Shinryu's Domain","Category":"sbTrialsEx","ID":"1989","Spoilers":true,"SpoilersUntil":"1794"},{"Name":"The Minstrel's Ballad: Tsukuyomi's Pain","Category":"sbTrialsEx","ID":"2060","Spoilers":true,"SpoilersUntil":"2098"},{"Name":"The Great Hunt (Extreme)","Category":"sbTrialsEx","ID":"2109"},{"Name":"The Jade Stoa (Extreme)","Category":"sbTrialsEx","ID":"2023"},{"Name":"Hells' Kier (Extreme)","Category":"sbTrialsEx","ID":"2117"},{"Name":"The Wreath of Snakes (Extreme)","Category":"sbTrialsEx","ID":"2165"}],"shbTrialsEx":[{"Name":"The Dancing Plague (Extreme)","Category":"shbTrialsEx","ID":"2385","Spoilers":true,"SpoilersUntil":"2294"},{"Name":"The Crown of the Immaculate (Extreme)","Category":"shbTrialsEx","ID":"2386","Spoilers":true,"SpoilersUntil":"2297"},{"Name":"Minstrel's Ballad: Hades's Elegy","Category":"shbTrialsEx","ID":"2441","Spoilers":true,"SpoilersUntil":"2298"},{"Name":"Cinder Drift (Extreme)","Category":"shbTrialsEx","ID":"2590"},{"Name":"Memoria Misera (Extreme)","Category":"shbTrialsEx","ID":"2586"},{"Name":"The Seat of Sacrifice (Extreme)","Category":"shbTrialsEx","ID":"2621","Spoilers":true,"SpoilersUntil":"2642"},{"Name":"Castrum Marinum (Extreme)","Category":"shbTrialsEx","ID":"2718"},{"Name":"The Cloud Deck (Extreme)","Category":"shbTrialsEx","ID":"2846"}],"arrRaids":[{"Name":"Labyrinth of the Ancients","Category":"arrRaids","ID":"883","Bold":true,"Spoilers":true},{"Name":"Syrcus Tower","Category":"arrRaids","ID":"995","Bold":true,"Spoilers":true},{"Name":"The World of Darkness","Category":"arrRaids","ID":"1068","Bold":true,"Spoilers":true},{"Name":"The Binding Coil of Bahamut","Category":"arrRaids","ID":"747"},{"Name":"The Second Coil of Bahamut","Category":"arrRaids","ID":"887"},{"Name":"The Final Coil of Bahamut","Category":"arrRaids","ID":"1040"}],"hwRaids":[{"Name":"The Void Ark","Category":"hwRaids","ID":"1399"},{"Name":"The Weeping City of Mhach","Category":"hwRaids","ID":"1574"},{"Name":"Dun Scaith","Category":"hwRaids","ID":"1689"},{"Name":"Alexander: Gordias","Category":"hwRaids","ID":"1228"},{"Name":"Alexander: Midas","Category":"hwRaids","ID":"1476"},{"Name":"Alexander: The Creator","Category":"hwRaids","ID":"1639"}],"sbRaids":[{"Name":"The Royal City of Rabanastre","Category":"sbRaids","ID":"1992"},{"Name":"The Ridorana Lighthouse","Category":"sbRaids","ID":"2106"},{"Name":"The Orbonne Monastery","Category":"sbRaids","ID":"2164"},{"Name":"Omega: Deltascape","Category":"sbRaids","ID":"1895"},{"Name":"Omega: Sigmascape","Category":"sbRaids","ID":"2024"},{"Name":"Omega: Alphascape","Category":"sbRaids","ID":"2118"}],"shbRaids":[{"Name":"The Copied Factory","Category":"shbRaids","ID":"2443"},{"Name":"The Puppets' Bunker","Category":"shbRaids","ID":"2622"},{"Name":"The Tower at Paradigm's Breach","Category":"shbRaids","ID":"2847"},{"Name":"Eden's Gate","Category":"shbRaids","ID":"2409"},{"Name":"Eden's Verse","Category":"shbRaids","ID":"2591"},{"Name":"Eden's Promise","Category":"shbRaids","ID":"2719"}],"arrRaidsSavUlt":[{"Name":"The Second Coil of Bahamut (Savage)","Category":"arrRaidsSavUlt","ID":"1000"}],"hwRaidsSavUlt":[{"Name":"Alexander: Gordias (Savage)","Category":"hwRaidsSavUlt","ID":"1231"},{"Name":"Alexander: Midas (Savage)","Category":"hwRaidsSavUlt","ID":"1479"},{"Name":"Alexander: The Creator (Savage)","Category":"hwRaidsSavUlt","ID":"1642"}],"sbRaidsSavUlt":[{"Name":"Omega: Deltascape (Savage)","Category":"sbRaidsSavUlt","ID":"1898"},{"Name":"Omega: Sigmascape (Savage)","Category":"sbRaidsSavUlt","ID":"2027"},{"Name":"Omega: Alphascape (Savage)","Category":"sbRaidsSavUlt","ID":"2121"},{"Name":"The Unending Coil of Bahamut (Ultimate)","Category":"sbRaidsSavUlt","ID":"1993"},{"Name":"The Minstrel's Ballad: The Weapon's Refrain (Ultimate)","Category":"sbRaidsSavUlt","ID":"2107"}],"shbRaidsSavUlt":[{"Name":"Eden's Gate (Savage)","Category":"shbRaidsSavUlt","ID":"2412"},{"Name":"Eden's Verse (Savage)","Category":"shbRaidsSavUlt","ID":"2594"},{"Name":"Eden's Promise (Savage)","Category":"shbRaidsSavUlt","ID":"2722"},{"Name":"The Epic of Alexander (Ultimate)","Category":"shbRaidsSavUlt","ID":"2444"}],"sbExploratory":[{"Name":"Baldesion Arsenal","Category":"sbExploratory","ID":"2227"}],"shbExploratory":[{"Name":"Castrum Lacus Litore","Category":"shbExploratory","ID":"2680"},{"Name":"Delubrum Reginae","Category":"shbExploratory","ID":"2762"},{"Name":"Delubrum Reginae (Savage)","Category":"shbExploratory","ID":"2765"},{"Name":"Dalriada","Category":"shbExploratory","ID":"2874"}]}